.flake8
.pre-commit-config.yaml
LICENSE
MANIFEST.in
README.md
environment.yml
mkdocs.yml
pyproject.toml
benchmarks/__init__.py
benchmarks/test_mo.py
benchmarks/test_ucb.py
docs/algorithms.md
docs/index.md
docs/installation.md
docs/api/evaluator.md
docs/api/generators.md
docs/api/vocs.md
docs/api/xopt.md
docs/api/generators/bayesian.md
docs/api/generators/genetic.md
docs/api/generators/scipy.md
docs/assets/Xopt-logo.png
docs/assets/xopt_overview.pdf
docs/hooks/zip_generator.py
docs/overrides/main.html
docs/stylesheets/extra.css
scripts/execute_notebooks.bash
scripts/run_benchmarks.py
scripts/run_examples.py
scripts/run_tests.py
xopt/__init__.py
xopt/_version.py
xopt/asynchronous.py
xopt/base.py
xopt/entrypoint.py
xopt/errors.py
xopt/evaluator.py
xopt/generator.py
xopt/log.py
xopt/numerical_optimizer.py
xopt/pydantic.py
xopt/utils.py
xopt/vocs.py
xopt.egg-info/PKG-INFO
xopt.egg-info/SOURCES.txt
xopt.egg-info/dependency_links.txt
xopt.egg-info/entry_points.txt
xopt.egg-info/requires.txt
xopt.egg-info/top_level.txt
xopt/generators/__init__.py
xopt/generators/deduplicated.py
xopt/generators/random.py
xopt/generators/utils.py
xopt/generators/bayesian/__init__.py
xopt/generators/bayesian/base_model.py
xopt/generators/bayesian/bax_generator.py
xopt/generators/bayesian/bayesian_exploration.py
xopt/generators/bayesian/bayesian_generator.py
xopt/generators/bayesian/expected_improvement.py
xopt/generators/bayesian/mggpo.py
xopt/generators/bayesian/mobo.py
xopt/generators/bayesian/multi_fidelity.py
xopt/generators/bayesian/objectives.py
xopt/generators/bayesian/time_dependent.py
xopt/generators/bayesian/turbo.py
xopt/generators/bayesian/upper_confidence_bound.py
xopt/generators/bayesian/utils.py
xopt/generators/bayesian/visualize.py
xopt/generators/bayesian/bax/__init__.py
xopt/generators/bayesian/bax/acquisition.py
xopt/generators/bayesian/bax/algorithms.py
xopt/generators/bayesian/bax/visualize.py
xopt/generators/bayesian/custom_botorch/__init__.py
xopt/generators/bayesian/custom_botorch/constrained_acquisition.py
xopt/generators/bayesian/custom_botorch/hessian_kernel.py
xopt/generators/bayesian/custom_botorch/heteroskedastic.py
