Metadata-Version: 2.4
Name: xopt
Version: 2.6.7
Summary: Flexible optimization of arbitrary problems in Python.
Author: Christopher Mayes, Ryan Roussel
License:                                  Apache License
Project-URL: Homepage, https://github.com/xopt-org/xopt
Classifier: Development Status :: 4 - Beta
Classifier: Natural Language :: English
Classifier: Programming Language :: Python :: 3
Classifier: Topic :: Scientific/Engineering
Requires-Python: >=3.10
License-File: LICENSE
Requires-Dist: deap
Requires-Dist: numpy
Requires-Dist: pydantic>=2.3
Requires-Dist: pyyaml
Requires-Dist: botorch>=0.12.0
Requires-Dist: scipy>=1.10.1
Requires-Dist: pandas
Requires-Dist: ipywidgets
Requires-Dist: tqdm
Requires-Dist: orjson
Requires-Dist: matplotlib
Provides-Extra: dev
Requires-Dist: pytest; extra == "dev"
Requires-Dist: pytest-cov; extra == "dev"
Requires-Dist: ffmpeg; extra == "dev"
Requires-Dist: pytest; extra == "dev"
Requires-Dist: pytest-cov; extra == "dev"
Requires-Dist: jupyterlab>=3; extra == "dev"
Requires-Dist: jupyterlab-lsp; extra == "dev"
Requires-Dist: python-lsp-server; extra == "dev"
Requires-Dist: pygments; extra == "dev"
Requires-Dist: dask; extra == "dev"
Requires-Dist: mpi4py; extra == "dev"
Provides-Extra: doc
Requires-Dist: mkdocs; extra == "doc"
Requires-Dist: mkdocs-jupyter; extra == "doc"
Requires-Dist: mkdocs-macros-plugin; extra == "doc"
Requires-Dist: mkdocs-material; extra == "doc"
Requires-Dist: mkdocstrings; extra == "doc"
Requires-Dist: mkdocstrings-python; extra == "doc"
Dynamic: license-file
